LICENSE
README.md
setup.py
plaid/__init__.py
plaid/api_client.py
plaid/configuration.py
plaid/exceptions.py
plaid/model_utils.py
plaid/rest.py
plaid/api/__init__.py
plaid/api/plaid_api.py
plaid/apis/__init__.py
plaid/model/__init__.py
plaid/model/aamva_analysis.py
plaid/model/aamva_detailed_match_result.py
plaid/model/aamva_match_result.py
plaid/model/account_access.py
plaid/model/account_assets.py
plaid/model/account_balance.py
plaid/model/account_base.py
plaid/model/account_base_nullable.py
plaid/model/account_filter.py
plaid/model/account_filter_subtypes.py
plaid/model/account_filters_response.py
plaid/model/account_holder_category.py
plaid/model/account_identity.py
plaid/model/account_identity_all_of.py
plaid/model/account_identity_document_upload.py
plaid/model/account_identity_document_upload_all_of.py
plaid/model/account_identity_match_score.py
plaid/model/account_identity_match_score_all_of.py
plaid/model/account_ids_with_updated_auth.py
plaid/model/account_ids_with_updated_identity.py
plaid/model/account_product_access.py
plaid/model/account_product_access_nullable.py
plaid/model/account_selection_cardinality.py
plaid/model/account_subtype.py
plaid/model/account_subtypes.py
plaid/model/account_type.py
plaid/model/account_verification_insights.py
plaid/model/account_verification_insights_account_number_format.py
plaid/model/account_verification_insights_network_status.py
plaid/model/account_verification_insights_previous_returns.py
plaid/model/accounts_balance_get_request.py
plaid/model/accounts_balance_get_request_options.py
plaid/model/accounts_get_request.py
plaid/model/accounts_get_request_options.py
plaid/model/accounts_get_response.py
plaid/model/ach_class.py
plaid/model/action_state.py
plaid/model/activity.py
plaid/model/activity_type.py
plaid/model/address.py
plaid/model/address_data.py
plaid/model/address_data_not_required.py
plaid/model/address_data_nullable.py
plaid/model/address_data_nullable_no_required_fields.py
plaid_python.egg-info/PKG-INFO
plaid_python.egg-info/SOURCES.txt
plaid_python.egg-info/dependency_links.txt
plaid_python.egg-info/not-zip-safe
plaid_python.egg-info/requires.txt
plaid_python.egg-info/top_level.txt
